bonjour/__init__.py
bonjour/bonjour.py
bonjourlowbackk-0.1.0.dist-info/METADATA
bonjourlowbackk-0.1.0.dist-info/WHEEL
bonjourlowbackk-0.1.0.dist-info/top_level.txt
bonjourlowbackk-0.1.0.dist-info/RECORD
