Metadata-Version: 2.2
Name: bonjourlowbackk
Version: 0.1.0
Summary: Test pour lowbackk
Home-page: https://github.com/LowBackk/Package-python
Author: Marco
Author-email: m.figueiredo367@gmail.com
Classifier: Programming Language :: Python :: 3
Classifier: License :: OSI Approved :: MIT License
Classifier: Operating System :: OS Independent
Requires-Python: >=3.6
Dynamic: author
Dynamic: author-email
Dynamic: classifier
Dynamic: description
Dynamic: description-content-type
Dynamic: home-page
Dynamic: requires-python
Dynamic: summary
